{
  "project_info": {
    "project_number": "933710790530",
    "project_id": "anydropmobile",
    "storage_bucket": "anydropmobile.firebasestorage.app"
  },
  "client": [
    {
      "client_info": {
        "mobilesdk_app_id": "1:933710790530:android:a1b08546cb7ba2d589199b",
        "android_client_info": {
          "package_name": "com.anydropapp"
        }
      },
      "oauth_client": [
        {
          "client_id": "933710790530-34dsmcpoc9vnqb854de1osph6h7b3vt0.apps.googleusercontent.com",
          "client_type": 1,
          "android_info": {
            "package_name": "com.anydropapp",
            "certificate_hash": "5e8f16062ea3cd2c4a0d547876baa6f38cabf625"
          }
        },
        {
          "client_id": "933710790530-il0tf3m2150lc5travsenl03ssi9g0e3.apps.googleusercontent.com",
          "client_type": 3
        }
      ],
      "api_key": [
        {
          "current_key": "AIzaSyCgyWTCJHqePVKQtOeM3iwU3uQmsEbMAfE"
        }
      ],
      "services": {
        "appinvite_service": {
          "other_platform_oauth_client": [
            {
              "client_id": "933710790530-il0tf3m2150lc5travsenl03ssi9g0e3.apps.googleusercontent.com",
              "client_type": 3
            },
            {
              "client_id": "933710790530-imrrqrjqb6ltf6g9it0glhhfbf3gdqrq.apps.googleusercontent.com",
              "client_type": 2,
              "ios_info": {
                "bundle_id": "com.anydropapp"
              }
            }
          ]
        }
      }
    }
  ],
  "configuration_version": "1"
}
